[
  {
    "name": "NotyStack Android",
    "desc": "Fully fledged android CRUD app based on different design patterns. Built using Java, XML, SQLite, Firebase, RoomDB, MVVM.",
    "image": "Doorkey.gif",
    "type" : "gif",
    "category": "all",
    "links": {
      "view": "https://www.linkedin.com/posts/jigar-sable_androiddev-androidstudio-java-activity-6955224473822199808-JT0j",
      "code": "https://github.com/jigar-sable/notystack-android"
    }
  },
  {
    "name": "NotyStack Android",
    "desc": "Fully fledged android CRUD app based on different design patterns. Built using Java, XML, SQLite, Firebase, RoomDB, MVVM.",
    "image": "Optimal_control.gif",
    "type" : "gif",
    "category": "all",
    "links": {
      "view": "https://www.linkedin.com/posts/jigar-sable_androiddev-androidstudio-java-activity-6955224473822199808-JT0j",
      "code": "https://github.com/jigar-sable/notystack-android"
    }
  },
  {
    "name": "NotyStack Android",
    "desc": "Fully fledged android CRUD app based on different design patterns. Built using Java, XML, SQLite, Firebase, RoomDB, MVVM.",
    "image": "optical_flow.gif",
    "type" : "gif",
    "category": "all",
    "links": {
      "view": "https://www.linkedin.com/posts/jigar-sable_androiddev-androidstudio-java-activity-6955224473822199808-JT0j",
      "code": "https://github.com/jigar-sable/notystack-android"
    }
  },
  {
    "name": "NotyStack Android",
    "desc": "Fully fledged android CRUD app based on different design patterns. Built using Java, XML, SQLite, Firebase, RoomDB, MVVM.",
    "image": "Particle_SLAM_Output.jpg",
    "type" : "image",
    "category": "all",
    "links": {
      "view": "https://www.linkedin.com/posts/jigar-sable_androiddev-androidstudio-java-activity-6955224473822199808-JT0j",
      "code": "https://github.com/jigar-sable/notystack-android"
    }
  },
  {
    "name": "NotyStack Android",
    "desc": "Fully fledged android CRUD app based on different design patterns. Built using Java, XML, SQLite, Firebase, RoomDB, MVVM.",
    "image": "EKF_SLAM_Output.jpg",
    "type" : "image",
    "category": "all",
    "links": {
      "view": "https://www.linkedin.com/posts/jigar-sable_androiddev-androidstudio-java-activity-6955224473822199808-JT0j",
      "code": "https://github.com/jigar-sable/notystack-android"
    }
  },
  {
    "name": "SPPU Engg Prep",
    "desc": "All in one SPPU Engineering resources. Built using Java, XML and Firebase.",
    "image": "windowRRT.png",
    "type" : "image",
    "category": "all",
    "links": {
      "view": "https://www.linkedin.com/posts/jigar-sable_androiddev-androidstudio-java-activity-6955224473822199808-JT0j",
      "code": "https://github.com/jigar-sable/sppu-prep-android"
    }
  }
]
